README.md
setup.cfg
setup.py
fragsifier/__init__.py
fragsifier/fragsifier.py
fragsifier/requirements.txt
fragsifier.egg-info/PKG-INFO
fragsifier.egg-info/SOURCES.txt
fragsifier.egg-info/dependency_links.txt
fragsifier.egg-info/entry_points.txt
fragsifier.egg-info/requires.txt
fragsifier.egg-info/top_level.txt
fragsifier/__pycache__/FSV_fragsify.cpython-36.pyc
fragsifier/__pycache__/FSV_preprocessing.cpython-36.pyc
fragsifier/__pycache__/FSV_preprocessing.cpython-37.pyc
fragsifier/__pycache__/FSV_string_functions.cpython-36.pyc
fragsifier/__pycache__/FSV_string_functions.cpython-37.pyc
fragsifier/__pycache__/TEMP_fragsify_runtime_params.cpython-36.pyc
fragsifier/__pycache__/TEMP_fragsify_runtime_params.cpython-37.pyc
fragsifier/__pycache__/fragsifier.cpython-36.pyc
fragsifier/models/FSV_reference_sequences_examples.csv
fragsifier/models/FSV_training_negative_examples.csv
fragsifier/models/allele_len_conversion_dict.pkl
fragsifier/models/allele_num_calculation_dict.pkl
fragsifier/models/class_le.pkl
fragsifier/models/flank_dict.pkl
fragsifier/models/key_loci_dict.pkl
fragsifier/models/seq_vectorizer.pkl
fragsifier/models/sequence_model.pkl
fragsifier/routines/__init__.py
fragsifier/routines/fragsify.py
fragsifier/routines/locus.config
fragsifier/routines/preprocessing.py
fragsifier/routines/string_functions.py
fragsifier/routines/__pycache__/__init__.cpython-36.pyc
fragsifier/routines/__pycache__/fragsify.cpython-36.pyc
fragsifier/routines/__pycache__/preprocessing.cpython-36.pyc
fragsifier/routines/__pycache__/string_functions.cpython-36.pyc