Metadata-Version: 1.2
Name: fragsifier
Version: 1.0.1
Summary: forensic STR sequence extraction tool
Home-page: https://github.com/alexyyl/FSV-Fragsifier
Author: Alexander YY Liu
Author-email: yliu575@aucklanduni.ac.nz
License: BSD 3-Clause
Download-URL: https://github.com/alexyyl/FSV-Fragsifier/releases/tag/v_1.0.1.tar.gz
Keywords: forensic STR,sequence extraction
Platform: UNKNOWN
Classifier: Development Status :: 4 - Beta
Classifier: Intended Audience :: Science/Research
Classifier: Topic :: Scientific/Engineering :: Bio-Informatics
Classifier: License :: OSI Approved :: BSD License
Classifier: Programming Language :: Python :: 3.6
Requires-Python: >=3.6
